LICENSE.md
MANIFEST.in
setup.py
jupyter_dashboards/__init__.py
jupyter_dashboards/_version.py
jupyter_dashboards/extensionapp.py
jupyter_dashboards.egg-info/PKG-INFO
jupyter_dashboards.egg-info/SOURCES.txt
jupyter_dashboards.egg-info/dependency_links.txt
jupyter_dashboards.egg-info/entry_points.txt
jupyter_dashboards.egg-info/requires.txt
jupyter_dashboards.egg-info/top_level.txt
jupyter_dashboards/__pycache__/__init__.cpython-36.pyc
jupyter_dashboards/__pycache__/_version.cpython-36.pyc
jupyter_dashboards/__pycache__/extensionapp.cpython-36.pyc
jupyter_dashboards/nbextension/notebook/link-css.js
jupyter_dashboards/nbextension/notebook/main.js
jupyter_dashboards/nbextension/notebook/bower_components/gridstack/.bower.json
jupyter_dashboards/nbextension/notebook/bower_components/gridstack/Gruntfile.js
jupyter_dashboards/nbextension/notebook/bower_components/gridstack/LICENSE
jupyter_dashboards/nbextension/notebook/bower_components/gridstack/README.md
jupyter_dashboards/nbextension/notebook/bower_components/gridstack/bower.json
jupyter_dashboards/nbextension/notebook/bower_components/gridstack/package.json
jupyter_dashboards/nbextension/notebook/bower_components/gridstack/demo/float.html
jupyter_dashboards/nbextension/notebook/bower_components/gridstack/demo/knockout.html
jupyter_dashboards/nbextension/notebook/bower_components/gridstack/demo/knockout2.html
jupyter_dashboards/nbextension/notebook/bower_components/gridstack/demo/nested.html
jupyter_dashboards/nbextension/notebook/bower_components/gridstack/demo/serialization.html
jupyter_dashboards/nbextension/notebook/bower_components/gridstack/demo/two.html
jupyter_dashboards/nbextension/notebook/bower_components/gridstack/dist/gridstack-extra.css
jupyter_dashboards/nbextension/notebook/bower_components/gridstack/dist/gridstack-extra.min.css
jupyter_dashboards/nbextension/notebook/bower_components/gridstack/dist/gridstack.css
jupyter_dashboards/nbextension/notebook/bower_components/gridstack/dist/gridstack.js
jupyter_dashboards/nbextension/notebook/bower_components/gridstack/dist/gridstack.min.css
jupyter_dashboards/nbextension/notebook/bower_components/gridstack/dist/gridstack.min.js
